{
    "Ar36": {
        "error": 1.3514455022333108e-08,
        "error_type": "",
        "fit": "previous",
        "references": [
            {
                "exclude": false,
                "record_id": "ba-01-n-6357"
            }
        ],
        "value": 6.423114581174536e-07
    },
    "Ar37": {
        "error": 1.4117090505248053e-07,
        "error_type": "",
        "fit": "previous",
        "references": [
            {
                "exclude": false,
                "record_id": "ba-01-n-6357"
            }
        ],
        "value": 3.894055054539841e-06
    },
    "Ar38": {
        "error": 1.4440760105331248e-07,
        "error_type": "",
        "fit": "previous",
        "references": [
            {
                "exclude": false,
                "record_id": "ba-01-n-6357"
            }
        ],
        "value": 3.3504956346897586e-07
    },
    "Ar39": {
        "error": 3.833059113146539e-07,
        "error_type": "",
        "fit": "previous",
        "references": [
            {
                "exclude": false,
                "record_id": "ba-01-n-6357"
            }
        ],
        "value": 3.0192564674708866e-06
    },
    "Ar40": {
        "error": 1.4116708635899583e-06,
        "error_type": "",
        "fit": "previous",
        "references": [
            {
                "exclude": false,
                "record_id": "ba-01-n-6357"
            }
        ],
        "value": 0.00016117372348607804
    }
}