{
    "Ar36": {
        "error": 1.6463004604416604e-07,
        "error_type": "SEM",
        "filter_outliers_dict": {
            "filter_outliers": true,
            "iterations": 1,
            "std_devs": 2
        },
        "fit": "linear",
        "value": 0.00015643912727126305
    },
    "Ar37": {
        "error": 2.8667322271654895e-07,
        "error_type": "SEM",
        "filter_outliers_dict": {
            "filter_outliers": true,
            "iterations": 1,
            "std_devs": 2
        },
        "fit": "linear",
        "value": -7.406174964381972e-07
    },
    "Ar38": {
        "error": 2.7742799440627675e-07,
        "error_type": "SEM",
        "filter_outliers_dict": {
            "filter_outliers": true,
            "iterations": 1,
            "std_devs": 2
        },
        "fit": "linear",
        "value": 3.0127952585450795e-05
    },
    "Ar39": {
        "error": 1.1827513757030596e-06,
        "error_type": "SEM",
        "filter_outliers_dict": {
            "filter_outliers": true,
            "iterations": 1,
            "std_devs": 2
        },
        "fit": "linear",
        "value": 5.370144851066005e-06
    },
    "Ar40": {
        "error": 6.366262230029231e-06,
        "error_type": "SEM",
        "filter_outliers_dict": {
            "filter_outliers": true,
            "iterations": 1,
            "std_devs": 2
        },
        "fit": "parabolic",
        "value": 0.049772158113452356
    }
}