{
    "Ar36": {
        "error": 1.0472090207940153e-08,
        "error_type": "",
        "fit": "previous",
        "references": [
            {
                "exclude": false,
                "record_id": "ba-01-n-6527"
            }
        ],
        "value": 4.112076863998788e-07
    },
    "Ar37": {
        "error": 2.214130158695814e-07,
        "error_type": "",
        "fit": "previous",
        "references": [
            {
                "exclude": false,
                "record_id": "ba-01-n-6527"
            }
        ],
        "value": -7.214698278401039e-08
    },
    "Ar38": {
        "error": 2.298248829442044e-07,
        "error_type": "",
        "fit": "previous",
        "references": [
            {
                "exclude": false,
                "record_id": "ba-01-n-6527"
            }
        ],
        "value": 2.0462529061557141e-07
    },
    "Ar39": {
        "error": 2.9766980311656536e-07,
        "error_type": "",
        "fit": "previous",
        "references": [
            {
                "exclude": false,
                "record_id": "ba-01-n-6527"
            }
        ],
        "value": -8.971995071939611e-08
    },
    "Ar40": {
        "error": 1.0159029043087059e-06,
        "error_type": "",
        "fit": "previous",
        "references": [
            {
                "exclude": false,
                "record_id": "ba-01-n-6527"
            }
        ],
        "value": 0.0001060114651276368
    }
}