{
    "Ax": {
        "error": 8.19708797007888e-08,
        "error_type": "SEM",
        "filter_outliers_dict": {
            "filter_outliers": false,
            "iterations": 1,
            "std_devs": 2
        },
        "fit": "average",
        "value": -1.1245799305429266e-06
    },
    "H2": {
        "error": 1.0887880739265374e-07,
        "error_type": "SEM",
        "filter_outliers_dict": {
            "filter_outliers": true,
            "iterations": 1,
            "std_devs": 2
        },
        "fit": "average",
        "value": -9.404490950056452e-07
    },
    "H4": {
        "error": 1.1042968200481418e-07,
        "error_type": "SEM",
        "filter_outliers_dict": {
            "filter_outliers": true,
            "iterations": 1,
            "std_devs": 2
        },
        "fit": "average",
        "value": -9.776355117333333e-07
    },
    "L2": {
        "error": 6.865585255793008e-08,
        "error_type": "SEM",
        "filter_outliers_dict": {
            "filter_outliers": true,
            "iterations": 1,
            "std_devs": 2
        },
        "fit": "average",
        "value": -1.5622293295667873e-06
    },
    "L4": {
        "error": 1.0666666666666665e-09,
        "error_type": "SEM",
        "filter_outliers_dict": {
            "filter_outliers": false,
            "iterations": 1,
            "std_devs": 2
        },
        "fit": "average",
        "value": 1.0666666666666667e-09
    }
}