{
    "baselines": [
        {
            "blob": "QkiQXLQA3ZBCcZVzNLXdckKNDuA0UTB0",
            "detector": "H3"
        },
        {
            "blob": "QkiQXLWhSulCcZVztgnfJUKNDuC1B3yb",
            "detector": "H1"
        },
        {
            "blob": "QkiQXLX0RSdCcZVztkKPREKNDuC2XGkF",
            "detector": "L1"
        },
        {
            "blob": "QkiQXLWHERlCcZVztaj/kEKNDuC0i1x3",
            "detector": "L3"
        },
        {
            "blob": "QkiQXDcb7CpCcZVzNyefMEKNDuA3E8fC",
            "detector": "L5"
        }
    ],
    "commit": "ccafac0afce5d73b7227af7ea3f271aadb30f7d4",
    "encoding": "base64",
    "format": ">ff",
    "signals": [
        {
            "blob": "QbmrAD1KP7hCCRrxPUikLw==",
            "detector": "H3",
            "isotope": "Ar40"
        },
        {
            "blob": "QbmrADcdPclCCRrxN2V2mw==",
            "detector": "H1",
            "isotope": "Ar39"
        },
        {
            "blob": "QbmrADfwQlpCCRrxN/DzwQ==",
            "detector": "L1",
            "isotope": "Ar38"
        },
        {
            "blob": "QbmrALV6w8tCCRrxs9SClA==",
            "detector": "L3",
            "isotope": "Ar37"
        },
        {
            "blob": "QbmrADkspndCCRrxOTAr4w==",
            "detector": "L5",
            "isotope": "Ar36"
        }
    ],
    "sniffs": [
        {
            "blob": null,
            "detector": "H3",
            "isotope": "Ar40"
        },
        {
            "blob": null,
            "detector": "H1",
            "isotope": "Ar39"
        },
        {
            "blob": null,
            "detector": "L1",
            "isotope": "Ar38"
        },
        {
            "blob": null,
            "detector": "L3",
            "isotope": "Ar37"
        },
        {
            "blob": null,
            "detector": "L5",
            "isotope": "Ar36"
        }
    ]
}