{
    "Ar36": {
        "error": 1.1184088907268245e-08,
        "error_type": "",
        "fit": "previous",
        "references": [
            {
                "exclude": false,
                "record_id": "ba-01-n-6194"
            }
        ],
        "value": 3.752144252333377e-07
    },
    "Ar37": {
        "error": 1.6395777140682048e-07,
        "error_type": "",
        "fit": "previous",
        "references": [
            {
                "exclude": false,
                "record_id": "ba-01-n-6194"
            }
        ],
        "value": 7.1301070298447e-08
    },
    "Ar38": {
        "error": 1.4974698821709452e-07,
        "error_type": "",
        "fit": "previous",
        "references": [
            {
                "exclude": false,
                "record_id": "ba-01-n-6194"
            }
        ],
        "value": -1.1964522483348341e-07
    },
    "Ar39": {
        "error": 2.275058709533008e-07,
        "error_type": "",
        "fit": "previous",
        "references": [
            {
                "exclude": false,
                "record_id": "ba-01-n-6194"
            }
        ],
        "value": 1.1172277609381932e-06
    },
    "Ar40": {
        "error": 7.363662821556247e-07,
        "error_type": "",
        "fit": "previous",
        "references": [
            {
                "exclude": false,
                "record_id": "ba-01-n-6194"
            }
        ],
        "value": 9.443351249105702e-05
    }
}